kafka_helper.py
kafka_helper-0.2.dist-info/METADATA
kafka_helper-0.2.dist-info/RECORD
kafka_helper-0.2.dist-info/WHEEL
kafka_helper-0.2.dist-info/top_level.txt
